pointcloud2/__init__.py
pointcloud2/messages.py
pointcloud2-0.2.3.dist-info/WHEEL
pointcloud2-0.2.3.dist-info/METADATA
pointcloud2-0.2.3.dist-info/RECORD
