Metadata-Version: 2.3
Name: pointcloud2
Version: 0.2.3
Summary: PointCloud2 lib for non ROS environments
Author: Marko Bausch
Author-email: Marko Bausch <60338487+mrkbac@users.noreply.github.com>
Classifier: Development Status :: 4 - Beta
Classifier: Intended Audience :: Developers
Classifier: Operating System :: OS Independent
Classifier: Programming Language :: Python
Classifier: Programming Language :: Python :: 3 :: Only
Classifier: Programming Language :: Python :: 3.8
Classifier: Programming Language :: Python :: 3.9
Classifier: Programming Language :: Python :: 3.10
Classifier: Programming Language :: Python :: 3.11
Classifier: License :: OSI Approved :: MIT License
Requires-Dist: numpy>1
Requires-Python: >=3.8
Project-URL: Source, https://github.com/mrkbac/pointcloud2
